itnpy/__init__.py
itnpy/_version.py
itnpy/custom.py
itnpy/itn.py
itnpy/vocab.py
itnpy-0.0.4.dist-info/LICENSE
itnpy-0.0.4.dist-info/METADATA
itnpy-0.0.4.dist-info/WHEEL
itnpy-0.0.4.dist-info/top_level.txt
itnpy-0.0.4.dist-info/RECORD
