Metadata-Version: 2.1
Name: itnpy
Version: 0.0.4
Summary: A simple, deterministic, and extensible approach to inverse text normalization for numbers
Home-page: https://github.com/Brandhsu/itnpy
Author: Brandhsu
Author-email: brandondhsu@gmail.com
License: MIT
Keywords: inverse text normalization,natural language processing,speech recognition,itn,nlp,asr
Classifier: Development Status :: 3 - Alpha
Classifier: Intended Audience :: Developers
Classifier: License :: OSI Approved :: MIT License
Classifier: Programming Language :: Python :: 3.7
Classifier: Programming Language :: Python :: 3.8
Classifier: Programming Language :: Python :: 3.9
Classifier: Programming Language :: Python :: 3.10
Requires-Python: >=3.7
License-File: LICENSE
Requires-Dist: pytest
Requires-Dist: pandas
